ovfexporter/OvfExporter.py
ovfexporter/VcenterInterfaces.py
ovfexporter/__init__.py
ovfexporter/ovfexport.py
ovfexporter-1.0.0.data/scripts/ovfexport
ovfexporter-1.0.0.dist-info/DESCRIPTION.rst
ovfexporter-1.0.0.dist-info/METADATA
ovfexporter-1.0.0.dist-info/RECORD
ovfexporter-1.0.0.dist-info/WHEEL
ovfexporter-1.0.0.dist-info/metadata.json
ovfexporter-1.0.0.dist-info/top_level.txt
