Metadata-Version: 2.0
Name: ovfexporter
Version: 1.0.0
Summary: Export a vCenter VM's vmdks and ovf descriptor to local file system
Home-page: https://github.com/ScienceLogic/ovfexporter/archive/1.0.0.zip
Author: Douglas Rohde
Author-email: drohde@sciencelogic.com
License: MIT
Keywords: export vmdk vCenter vm,ami
Platform: UNKNOWN
Classifier: Development Status :: 4 - Beta
Classifier: Intended Audience :: System Administrators
Classifier: Topic :: Other/Nonlisted Topic
Classifier: License :: OSI Approved :: MIT License
Classifier: Programming Language :: Python :: 2.7
Requires-Dist: pysphere
Requires-Dist: pyvmomi
